{
    "experiment_name": "exp_70_30_nostem_iter2_h128_d0.2_lr0.001_b32_l2",
    "scenario": {
        "split": "70_30",
        "stemming": false
    },
    "params": {
        "hidden_size": 128,
        "dropout": 0.2,
        "learning_rate": 0.001,
        "batch_size": 32,
        "gru_layers": 2
    },
    "history": {
        "train_loss": [
            0.5209230760215549,
            0.47127460559726925,
            0.4439271274917677,
            0.39993799421996945,
            0.3475842996703685
        ],
        "val_loss": [
            0.4912904225515597,
            0.48585582592270593,
            0.47897913058598834,
            0.5008495495174871,
            0.5482716144937457
        ],
        "val_f1": [
            0.7373796088081802,
            0.7459597530493792,
            0.7561394816257347,
            0.7573872604385878,
            0.74968811841635
        ],
        "val_metrics": [
            {
                "0": {
                    "precision": 0.7681845062093435,
                    "recall": 0.9167254763585039,
                    "f1-score": 0.8359073359073359,
                    "support": 1417.0
                },
                "1": {
                    "precision": 0.7114914425427873,
                    "recall": 0.4260614934114202,
                    "f1-score": 0.532967032967033,
                    "support": 683.0
                },
                "accuracy": 0.7571428571428571,
                "macro avg": {
                    "precision": 0.7398379743760655,
                    "recall": 0.6713934848849621,
                    "f1-score": 0.6844371844371844,
                    "support": 2100.0
                },
                "weighted avg": {
                    "precision": 0.7497457621692207,
                    "recall": 0.7571428571428571,
                    "f1-score": 0.7373796088081802,
                    "support": 2100.0
                }
            },
            {
                "0": {
                    "precision": 0.7775757575757576,
                    "recall": 0.9054340155257586,
                    "f1-score": 0.8366481904140854,
                    "support": 1417.0
                },
                "1": {
                    "precision": 0.7022222222222222,
                    "recall": 0.46266471449487556,
                    "f1-score": 0.5578111209179171,
                    "support": 683.0
                },
                "accuracy": 0.7614285714285715,
                "macro avg": {
                    "precision": 0.7398989898989898,
                    "recall": 0.6840493650103171,
                    "f1-score": 0.6972296556660013,
                    "support": 2100.0
                },
                "weighted avg": {
                    "precision": 0.7530679172679172,
                    "recall": 0.7614285714285715,
                    "f1-score": 0.7459597530493792,
                    "support": 2100.0
                }
            },
            {
                "0": {
                    "precision": 0.7925363693864642,
                    "recall": 0.8842625264643613,
                    "f1-score": 0.8358905937291528,
                    "support": 1417.0
                },
                "1": {
                    "precision": 0.6840077071290944,
                    "recall": 0.5197657393850659,
                    "f1-score": 0.5906821963394343,
                    "support": 683.0
                },
                "accuracy": 0.7657142857142857,
                "macro avg": {
                    "precision": 0.7382720382577793,
                    "recall": 0.7020141329247136,
                    "f1-score": 0.7132863950342936,
                    "support": 2100.0
                },
                "weighted avg": {
                    "precision": 0.7572387139951388,
                    "recall": 0.7657142857142857,
                    "f1-score": 0.7561394816257347,
                    "support": 2100.0
                }
            },
            {
                "0": {
                    "precision": 0.819268635724332,
                    "recall": 0.8221594918842625,
                    "f1-score": 0.8207115181401902,
                    "support": 1417.0
                },
                "1": {
                    "precision": 0.6283185840707964,
                    "recall": 0.623718887262079,
                    "f1-score": 0.6260102865540044,
                    "support": 683.0
                },
                "accuracy": 0.7576190476190476,
                "macro avg": {
                    "precision": 0.7237936098975641,
                    "recall": 0.7229391895731707,
                    "f1-score": 0.7233609023470973,
                    "support": 2100.0
                },
                "weighted avg": {
                    "precision": 0.7571644046389201,
                    "recall": 0.7576190476190476,
                    "f1-score": 0.7573872604385878,
                    "support": 2100.0
                }
            },
            {
                "0": {
                    "precision": 0.7941558441558442,
                    "recall": 0.863091037402964,
                    "f1-score": 0.8271897193101116,
                    "support": 1417.0
                },
                "1": {
                    "precision": 0.6535714285714286,
                    "recall": 0.5358711566617862,
                    "f1-score": 0.588897827835881,
                    "support": 683.0
                },
                "accuracy": 0.7566666666666667,
                "macro avg": {
                    "precision": 0.7238636363636364,
                    "recall": 0.699481097032375,
                    "f1-score": 0.7080437735729963,
                    "support": 2100.0
                },
                "weighted avg": {
                    "precision": 0.748432436611008,
                    "recall": 0.7566666666666667,
                    "f1-score": 0.74968811841635,
                    "support": 2100.0
                }
            }
        ]
    },
    "best_f1": 0.7573872604385878,
    "final_metrics": {
        "0": {
            "precision": 0.7941558441558442,
            "recall": 0.863091037402964,
            "f1-score": 0.8271897193101116,
            "support": 1417.0
        },
        "1": {
            "precision": 0.6535714285714286,
            "recall": 0.5358711566617862,
            "f1-score": 0.588897827835881,
            "support": 683.0
        },
        "accuracy": 0.7566666666666667,
        "macro avg": {
            "precision": 0.7238636363636364,
            "recall": 0.699481097032375,
            "f1-score": 0.7080437735729963,
            "support": 2100.0
        },
        "weighted avg": {
            "precision": 0.748432436611008,
            "recall": 0.7566666666666667,
            "f1-score": 0.74968811841635,
            "support": 2100.0
        }
    }
}